worktory/__init__.py
worktory/connection/__init__.py
worktory/connection/base_wrapper.py
worktory/connection/fabric.py
worktory/connection/wrappers/__init__.py
worktory/connection/wrappers/netmiko_wrapper.py
worktory/connection/wrappers/scrapli_wrapper.py
worktory/connection/wrappers/unicon_wrapper.py
worktory/device/__init__.py
worktory/device/device.py
worktory/inventory/__init__.py
worktory/inventory/inventory.py
worktory/parsers/__init__.py
worktory/parsers/base_parser.py
worktory/parsers/fabric.py
worktory/parsers/wrappers/__init__.py
worktory/parsers/wrappers/default.py
worktory-0.1.2.dist-info/LICENSE
worktory-0.1.2.dist-info/WHEEL
worktory-0.1.2.dist-info/METADATA
worktory-0.1.2.dist-info/RECORD
