Metadata-Version: 2.1
Name: worktory
Version: 0.1.2
Summary: Network Automation Inventory
Home-page: https://github.com/renatoalmeidaoliveira/Worktory
License: MIT
Author: Renato Almeida de Oliveira
Author-email: renato.almeida.oliveira@gmail.com
Requires-Python: >=3.8
Classifier: License :: OSI Approved :: MIT License
Classifier: Programming Language :: Python :: 3
Classifier: Programming Language :: Python :: 3.10
Classifier: Programming Language :: Python :: 3.8
Classifier: Programming Language :: Python :: 3.9
Requires-Dist: asyncssh (>=2.7.2)
Requires-Dist: genie (>=21.7)
Requires-Dist: netmiko (>=3.4.0)
Requires-Dist: ntc-templates (>=2.3.2)
Requires-Dist: pyats (>=21.7)
Requires-Dist: scrapli-community (>=2021.7.30)
Requires-Dist: scrapli[ssh2] (>=2021.7.30)
Project-URL: Repository, https://github.com/renatoalmeidaoliveira/Worktory
